setup.py
bidimensional/__init__.py
bidimensional/bidimensional.py
twentytab_model_to_bidimensional.egg-info/PKG-INFO
twentytab_model_to_bidimensional.egg-info/SOURCES.txt
twentytab_model_to_bidimensional.egg-info/dependency_links.txt
twentytab_model_to_bidimensional.egg-info/top_level.txt