Metadata-Version: 1.0
Name: twentytab-model-to-bidimensional
Version: 0.2
Summary: A django app that returns a bidimensional representation of a given model and queryset following foreign keys recursively
Home-page: https://github.com/20tab/twentytab-model-to-bidimensional
Author: 20tab S.r.l.
Author-email: info@20tab.com
License: MIT License
Platform: UNKNOWN
